zfs_backup
