Metadata-Version: 1.0
Name: zfs-backup
Version: 0.1.2
Summary: Backup tool using ZFS snapshots
Home-page: https://github.com/Stupeflix/zfs_backup
Author: Stupeflix
Author-email: thomas@stupeflix.com
License: MIT
Keywords: backup zfs snapshot postgres postgresql psql mysql
Platform: UNKNOWN
